chrombpnet/__init__.py
chrombpnet/bpnet.py
chrombpnet/chrombpnet.py
chrombpnet/data_config.py
chrombpnet/data_utils.py
chrombpnet/dataset.py
chrombpnet/genome.py
chrombpnet/interpret.py
chrombpnet/logger.py
chrombpnet/main.py
chrombpnet/metrics.py
chrombpnet/metrics_utils.py
chrombpnet/model_config.py
chrombpnet/model_wrappers.py
chrombpnet/parse_utils.py
chrombpnet/snp_scoring.py
chrombpnet/snp_utils.py
chrombpnet/variant_summary_across_folds.py
chrombpnet_pytorch-0.0.3.dist-info/METADATA
chrombpnet_pytorch-0.0.3.dist-info/WHEEL
chrombpnet_pytorch-0.0.3.dist-info/entry_points.txt
chrombpnet_pytorch-0.0.3.dist-info/licenses/LICENSE
chrombpnet_pytorch-0.0.3.dist-info/RECORD
