Metadata-Version: 2.4
Name: chrombpnet_pytorch
Version: 0.0.3
Summary: ChromBPNet pytorch
Project-URL: Documentation, https://cookiecutter-scverse-instance.readthedocs.io/
Project-URL: Source, https://github.com/scverse/cookiecutter-scverse-instance
Project-URL: Home-page, https://github.com/scverse/cookiecutter-scverse-instance
Author: Lei Xiong
Author-email: jsxlei@gmail.com
Maintainer-email: Lei Xiong <jsxlei@gmail.com>
License: BSD 3-Clause License
License-File: LICENSE
Requires-Python: >=3.7
Requires-Dist: deepdish
Requires-Dist: h5py
Requires-Dist: lightning
Requires-Dist: matplotlib
Requires-Dist: pooch
Requires-Dist: pybedtools
Requires-Dist: pybigwig
Requires-Dist: pyfaidx
Requires-Dist: session-info
Requires-Dist: tangermeme
Requires-Dist: torch
Requires-Dist: weasyprint
Provides-Extra: dev
Requires-Dist: pre-commit; extra == 'dev'
Requires-Dist: twine>=4.0.2; extra == 'dev'
Provides-Extra: doc
Requires-Dist: docutils!=0.18.*,!=0.19.*,>=0.8; extra == 'doc'
Requires-Dist: ipykernel; extra == 'doc'
Requires-Dist: ipython; extra == 'doc'
Requires-Dist: myst-nb; extra == 'doc'
Requires-Dist: pandas; extra == 'doc'
Requires-Dist: sphinx-autodoc-typehints; extra == 'doc'
Requires-Dist: sphinx-book-theme>=1.0.0; extra == 'doc'
Requires-Dist: sphinx-copybutton; extra == 'doc'
Requires-Dist: sphinx>=4; extra == 'doc'
Requires-Dist: sphinxcontrib-bibtex>=1.0.0; extra == 'doc'
Requires-Dist: sphinxext-opengraph; extra == 'doc'
Provides-Extra: test
Requires-Dist: coverage; extra == 'test'
Requires-Dist: pytest; extra == 'test'
